pycor/VERS.py
pycor/VERSION.py
pycor/__init__.py
pycor/classifier.py
pycor/dictionary.py
pycor/dictionary2.py
pycor/docresolver.py
pycor/keywordutils.py
pycor/korlang.py
pycor/korlangmodel.py
pycor/kormorpheme.py
pycor/korutils.py
pycor/langmodel.py
pycor/morpheme.py
pycor/parser.py
pycor/resolver.py
pycor/scoring.py
pycor/speechmodel.py
pycor/syntagm.py
pycor/trainer.py
pycor/utils.py
pycor/bisect/__init__.py
pycor/bisect/chain.py
pycor/bisect/tree.py
pycor/dev/__init__.py
pycor/dev/model.py
pycor/res/__init__.py
pycor/res/collocresolver.1.py
pycor/res/collocresolver.py
pycor/res/rhizomeresolver.py
pycor/res/sentenceresolver.py
pycor/res/wikiresolver.py
pycor/res/yongeonresolver.py
pycor/std/__init__.py
pycor/std/aux.py
pycor/std/collocation.py
pycor/std/irregular.py
pycor/std/korstandard.py
pycor/std/single.py
pycor/std/stdsyntagm.py
pycor/std/stem.py
pycor/std/suffix.py
pycor-0.0.8.dist-info/METADATA
pycor-0.0.8.dist-info/RECORD
pycor-0.0.8.dist-info/WHEEL
pycor-0.0.8.dist-info/top_level.txt
