Metadata-Version: 2.1
Name: pycor
Version: 0.0.8
Summary: Python based Korean Language Processing Lib, Contextual Parser
Home-page: https://github.com/ontolog-so/pycor
Author: Ikchan Kwon
Author-email: ontolog.so@gmail.com
License: MIT
Download-URL: https://github.com/ontolog-so/pykor/archive/0.0.8.tar.gz
Keywords: Korean NLP,POS Tagger,Natural Language Contextual Parser
Platform: UNKNOWN
Classifier: Programming Language :: Python :: 3.5
Requires-Python: >=3.5
Requires-Dist: pandas
